dimepy/__init__.py
dimepy/scan.py
dimepy/spectrum.py
dimepy/spectrumList.py
dimepy/utils.py
DIMEpy-1.0.1.dist-info/LICENSE
DIMEpy-1.0.1.dist-info/METADATA
DIMEpy-1.0.1.dist-info/WHEEL
DIMEpy-1.0.1.dist-info/top_level.txt
DIMEpy-1.0.1.dist-info/RECORD
