Metadata-Version: 2.1
Name: DIMEpy
Version: 1.0.1
Summary: Python package for the high-throughput nontargeted metabolite fingerprinting of nominal mass direct injection mass spectrometry.
Home-page: https://github.com/AberystwythSystemsBiology/DIMEpy
Author: Keiron O'Shea
License: UNKNOWN
Keywords: metabolomics,omics,processing
Platform: UNKNOWN
Classifier: Development Status :: 5 - Production/Stable
Classifier: Intended Audience :: Science/Research
Classifier: Programming Language :: Python :: 3
Classifier: Programming Language :: Python :: 3.7
Classifier: Topic :: Scientific/Engineering :: Bio-Informatics
Classifier: License :: OSI Approved :: GNU General Public License v3 (GPLv3)
Classifier: Operating System :: OS Independent
Requires-Python: >=3.7
Requires-Dist: certifi (==2020.6.20)
Requires-Dist: cycler (==0.10.0)
Requires-Dist: joblib (==0.14.0)
Requires-Dist: kiwisolver (==1.2.0)
Requires-Dist: matplotlib (==3.3.1)
Requires-Dist: numpy (==1.19.1)
Requires-Dist: Pillow (==7.2.0)
Requires-Dist: pymzml (==2.3.1)
Requires-Dist: pyparsing (==2.4.7)
Requires-Dist: python-dateutil (==2.8.1)
Requires-Dist: regex (==2020.7.14)
Requires-Dist: scikit-learn (==0.23.2)
Requires-Dist: scipy (==1.5.2)
Requires-Dist: six (==1.15.0)
Requires-Dist: sklearn (==0.0)
Requires-Dist: threadpoolctl (==2.1.0)
